{
  "construct-by-self mind mapping": 0,
  "construct-on-scaffold mind mapping": 0,
  "design-based learning": 1,
  "evidence-centred design approach": 0,
  "gamification": 5,
  "reverse engineering pedagogy": 0,
  "technology-enhanced learning": 0,
  "collaborative learning": 4,
  "cooperative learning": 1,
  "flipped classroom": 3,
  "game-based learning": 6,
  "inquiry-based learning": 0,
  "personalized learning": 3,
  "problem-based learning": 1,
  "project-based learning": 5,
  "universal design for learning": 0
}